{
  "encounterId": 3176,
  "bossName": "Imperator Averzian",
  "bossSlug": "spire_h1_afuzan",
  "zoneId": 46,
  "zoneName": "VS / DR / MQD",
  "difficulty": 4,
  "page": 1,
  "pageSize": 50,
  "region": "CN",
  "hasMorePages": true,
  "total": 50,
  "rankings": [
    {
      "rank": 1,
      "duration": 227572,
      "startTime": 1774098130016,
      "reportCode": "bq6CdBQDhMjcLtJv",
      "fightId": 43,
      "reportStartTime": 1774092413007,
      "bracketData": 250.467,
      "size": 30,
      "deaths": 1,
      "tanks": 2,
      "healers": 5,
      "melee": 6,
      "ranged": 17,
      "server": {
        "id": 583,
        "name": "冰风岗",
        "region": "CN"
      },
      "guild": {
        "id": 797740,
        "name": "K F C",
        "faction": 1
      },
      "damageTaken": 128518493
    },
    {
      "rank": 2,
      "duration": 230698,
      "startTime": 1774095422044,
      "reportCode": "FYKPz3Cpdw4G8Tyx",
      "fightId": 5,
      "reportStartTime": 1774094190606,
      "bracketData": 249.867,
      "size": 30,
      "deaths": 0,
      "tanks": 2,
      "healers": 5,
      "melee": 10,
      "ranged": 13,
      "server": {
        "id": 564,
        "name": "主宰之剑",
        "region": "CN"
      },
      "guild": {
        "id": 7731,
        "name": "永恒理想",
        "faction": 0
      },
      "damageTaken": 101854562
    },
    {
      "rank": 3,
      "duration": 232447,
      "startTime": 1774270978977,
      "reportCode": "bXcZABRdtmxgyhPz",
      "fightId": 6,
      "reportStartTime": 1774266898409,
      "bracketData": 255.148,
      "size": 27,
      "deaths": 0,
      "tanks": 2,
      "healers": 5,
      "melee": 4,
      "ranged": 16,
      "server": {
        "id": 571,
        "name": "伊瑟拉",
        "region": "CN"
      },
      "guild": {
        "id": 578329,
        "name": "醉星辰",
        "faction": 0
      },
      "damageTaken": 104537051
    },
    {
      "rank": 4,
      "duration": 236285,
      "startTime": 1774008226657,
      "reportCode": "8BDxrcGnCP9fNyJd",
      "fightId": 2,
      "reportStartTime": 1774007482965,
      "bracketData": 249.933,
      "size": 30,
      "deaths": 0,
      "tanks": 2,
      "healers": 5,
      "melee": 6,
      "ranged": 17,
      "server": {
        "id": 832,
        "name": "贫瘠之地",
        "region": "CN"
      },
      "guild": {
        "id": 161301,
        "name": "利刃",
        "faction": 1
      },
      "damageTaken": 115813383
    },
    {
      "rank": 5,
      "duration": 238330,
      "startTime": 1774007095455,
      "reportCode": "7ckbhL8Q1DdJMFa9",
      "fightId": 3,
      "reportStartTime": 1774006611251,
      "bracketData": 249.7,
      "size": 30,
      "deaths": 0,
      "tanks": 2,
      "healers": 5,
      "melee": 9,
      "ranged": 14,
      "server": {
        "id": 790,
        "name": "罗宁",
        "region": "CN"
      },
      "guild": {
        "id": 406009,
        "name": "冷涩",
        "faction": 0
      },
      "damageTaken": 122929120
    },
    {
      "rank": 6,
      "duration": 238599,
      "startTime": 1774093752345,
      "reportCode": "AhGTLjDgwZNP27qa",
      "fightId": 2,
      "reportStartTime": 1774066049997,
      "bracketData": 251.067,
      "size": 30,
      "deaths": 0,
      "tanks": 2,
      "healers": 6,
      "melee": 6,
      "ranged": 16,
      "server": {
        "id": 666,
        "name": "布兰卡德",
        "region": "CN"
      },
      "guild": {
        "id": 655358,
        "name": "炉火糖粥",
        "faction": 1
      },
      "damageTaken": 108551228
    },
    {
      "rank": 7,
      "duration": 239621,
      "startTime": 1774008411230,
      "reportCode": "xztRDw9nJANZ4bP3",
      "fightId": 3,
      "reportStartTime": 1774008046308,
      "bracketData": 249.5,
      "size": 30,
      "deaths": 0,
      "tanks": 2,
      "healers": 5,
      "melee": 9,
      "ranged": 14,
      "server": {
        "id": 832,
        "name": "贫瘠之地",
        "region": "CN"
      },
      "guild": {
        "id": 390751,
        "name": "寒冰魔神",
        "faction": 1
      },
      "damageTaken": 119430866
    },
    {
      "rank": 8,
      "duration": 239630,
      "startTime": 1774098417735,
      "reportCode": "NdM6Znr7pHXbVLCf",
      "fightId": 2,
      "reportStartTime": 1774097824211,
      "bracketData": 253.552,
      "size": 29,
      "deaths": 1,
      "tanks": 2,
      "healers": 6,
      "melee": 9,
      "ranged": 12,
      "server": {
        "id": 745,
        "name": "烈焰峰",
        "region": "CN"
      },
      "guild": {
        "id": 30401,
        "name": "一塌糊涂",
        "faction": 1
      },
      "damageTaken": 103274418
    },
    {
      "rank": 9,
      "duration": 239631,
      "startTime": 1774098416378,
      "reportCode": "Rbm148aqy3Z2AfGj",
      "fightId": 56,
      "reportStartTime": 1774090382873,
      "bracketData": 253.552,
      "size": 29,
      "deaths": 1,
      "tanks": 2,
      "healers": 6,
      "melee": 9,
      "ranged": 12,
      "server": {
        "id": 745,
        "name": "烈焰峰",
        "region": "CN"
      },
      "guild": {
        "id": 765904,
        "name": "狼哥打的不队",
        "faction": 0
      },
      "damageTaken": 103274418
    },
    {
      "rank": 10,
      "duration": 240182,
      "startTime": 1774269390939,
      "reportCode": "g1CZn9zDKhqHRWmV",
      "fightId": 9,
      "reportStartTime": 1774268022942,
      "bracketData": 253.348,
      "size": 23,
      "deaths": 1,
      "tanks": 2,
      "healers": 5,
      "melee": 6,
      "ranged": 10,
      "server": {
        "id": 569,
        "name": "伊森利恩",
        "region": "CN"
      },
      "guild": {
        "id": 648707,
        "name": "你为什么不和我打游戏",
        "faction": 1
      },
      "damageTaken": 95227195
    },
    {
      "rank": 11,
      "duration": 240644,
      "startTime": 1774271013628,
      "reportCode": "ZxqdmJzLB6cbgPVW",
      "fightId": 3,
      "reportStartTime": 1774269376981,
      "bracketData": 252.4,
      "size": 25,
      "deaths": 0,
      "tanks": 2,
      "healers": 5,
      "melee": 5,
      "ranged": 13,
      "server": {
        "id": 676,
        "name": "影之哀伤",
        "region": "CN"
      },
      "guild": {
        "id": 545627,
        "name": "年輪",
        "faction": 1
      },
      "damageTaken": 97704910
    },
    {
      "rank": 12,
      "duration": 241069,
      "startTime": 1774009218049,
      "reportCode": "yzwfkc7q1xmj8ng3",
      "fightId": 6,
      "reportStartTime": 1774007865920,
      "bracketData": 250.96,
      "size": 25,
      "deaths": 0,
      "tanks": 2,
      "healers": 5,
      "melee": 5,
      "ranged": 13,
      "server": {
        "id": 790,
        "name": "罗宁",
        "region": "CN"
      },
      "guild": {
        "id": 689988,
        "name": "行星防御理事会",
        "faction": 0
      },
      "damageTaken": 88231700
    },
    {
      "rank": 13,
      "duration": 242773,
      "startTime": 1774008728687,
      "reportCode": "pm9rZ17qcjh6WF3z",
      "fightId": 4,
      "reportStartTime": 1774007211511,
      "bracketData": 249.3,
      "size": 30,
      "deaths": 0,
      "tanks": 2,
      "healers": 5,
      "melee": 6,
      "ranged": 17,
      "server": {
        "id": 720,
        "name": "死亡之翼",
        "region": "CN"
      },
      "guild": {
        "id": 660914,
        "name": "ALL JB HOMIE",
        "faction": 1
      },
      "damageTaken": 107352907
    },
    {
      "rank": 14,
      "duration": 243774,
      "startTime": 1774008877707,
      "reportCode": "NwcPrBDkAXKCL6jn",
      "fightId": 26,
      "reportStartTime": 1774007087585,
      "bracketData": 250.87,
      "size": 23,
      "deaths": 0,
      "tanks": 2,
      "healers": 5,
      "melee": 5,
      "ranged": 11,
      "server": {
        "id": 770,
        "name": "白银之手",
        "region": "CN"
      },
      "guild": {
        "id": 770798,
        "name": "Fishing Squad",
        "faction": 0
      },
      "damageTaken": 85418397
    },
    {
      "rank": 15,
      "duration": 244059,
      "startTime": 1774014558055,
      "reportCode": "GVB9AKZzgMT8yqjb",
      "fightId": 9,
      "reportStartTime": 1774011527523,
      "bracketData": 250.087,
      "size": 23,
      "deaths": 0,
      "tanks": 2,
      "healers": 4,
      "melee": 6,
      "ranged": 11,
      "server": {
        "id": 676,
        "name": "影之哀伤",
        "region": "CN"
      },
      "guild": {
        "id": 640224,
        "name": "若年",
        "faction": 1
      },
      "damageTaken": 85126680
    },
    {
      "rank": 16,
      "duration": 244998,
      "startTime": 1774008421834,
      "reportCode": "x2NDmL3CBr1XtnYy",
      "fightId": 6,
      "reportStartTime": 1774007452640,
      "bracketData": 247.6,
      "size": 30,
      "deaths": 0,
      "tanks": 2,
      "healers": 5,
      "melee": 10,
      "ranged": 13,
      "server": {
        "id": 770,
        "name": "白银之手",
        "region": "CN"
      },
      "guild": {
        "id": 220754,
        "name": "Withered Wind",
        "faction": 0
      },
      "damageTaken": 115260842
    },
    {
      "rank": 17,
      "duration": 245165,
      "startTime": 1774269679154,
      "reportCode": "w1RvYkbWxApLDam4",
      "fightId": 1,
      "reportStartTime": 1774269145283,
      "bracketData": 254.222,
      "size": 27,
      "deaths": 1,
      "tanks": 2,
      "healers": 5,
      "melee": 9,
      "ranged": 11,
      "server": {
        "id": 676,
        "name": "影之哀伤",
        "region": "CN"
      },
      "guild": {
        "id": 597736,
        "name": "不羁的肥皂厂12.0",
        "faction": 1
      },
      "damageTaken": 114103836
    },
    {
      "rank": 18,
      "duration": 245462,
      "startTime": 1774181510514,
      "reportCode": "gKQDJMkB1TCZwpqd",
      "fightId": 8,
      "reportStartTime": 1774146532844,
      "bracketData": 252.833,
      "size": 30,
      "deaths": 0,
      "tanks": 2,
      "healers": 6,
      "melee": 6,
      "ranged": 16,
      "server": {
        "id": 854,
        "name": "金色平原",
        "region": "CN"
      },
      "guild": {
        "id": 802679,
        "name": "咏冻黎明12.0",
        "faction": 0
      },
      "damageTaken": 103697690
    },
    {
      "rank": 19,
      "duration": 245515,
      "startTime": 1774271480235,
      "reportCode": "QLr84dcRDwWXhpJx",
      "fightId": 10,
      "reportStartTime": 1774269000763,
      "bracketData": 253.6,
      "size": 30,
      "deaths": 4,
      "tanks": 2,
      "healers": 5,
      "melee": 7,
      "ranged": 16,
      "server": {
        "id": 770,
        "name": "白银之手",
        "region": "CN"
      },
      "guild": {
        "id": 779537,
        "name": "北宇治吹奏部",
        "faction": 0
      },
      "damageTaken": 124107095
    },
    {
      "rank": 20,
      "duration": 245931,
      "startTime": 1774267599126,
      "reportCode": "w8bcWQMV7BPJqtvK",
      "fightId": 3,
      "reportStartTime": 1774266579185,
      "bracketData": 253.444,
      "size": 27,
      "deaths": 1,
      "tanks": 2,
      "healers": 5,
      "melee": 7,
      "ranged": 13,
      "server": {
        "id": 583,
        "name": "冰风岗",
        "region": "CN"
      },
      "guild": {
        "id": 668542,
        "name": "智盛",
        "faction": 1
      },
      "damageTaken": 101853652
    },
    {
      "rank": 21,
      "duration": 246691,
      "startTime": 1774015791309,
      "reportCode": "gQCHT32ApGfkrWYc",
      "fightId": 3,
      "reportStartTime": 1774014496715,
      "bracketData": 250.63,
      "size": 27,
      "deaths": 0,
      "tanks": 2,
      "healers": 5,
      "melee": 6,
      "ranged": 14,
      "server": {
        "id": 770,
        "name": "白银之手",
        "region": "CN"
      },
      "guild": {
        "id": 648934,
        "name": "天涯旅社开荒团",
        "faction": 0
      },
      "damageTaken": 92328686
    },
    {
      "rank": 22,
      "duration": 246930,
      "startTime": 1773936943117,
      "reportCode": "qLgRkNMGJDfaXVh9",
      "fightId": 60,
      "reportStartTime": 1773922976738,
      "bracketData": 244.267,
      "size": 30,
      "deaths": 0,
      "tanks": 2,
      "healers": 6,
      "melee": 10,
      "ranged": 12,
      "server": {
        "id": 887,
        "name": "鬼雾峰",
        "region": "CN"
      },
      "guild": {
        "id": 507574,
        "name": "Scary maze 9.0",
        "faction": 1
      },
      "damageTaken": 117005272
    },
    {
      "rank": 23,
      "duration": 247067,
      "startTime": 1774272700948,
      "reportCode": "PkNFT1BG86KWt2bA",
      "fightId": 9,
      "reportStartTime": 1774270690799,
      "bracketData": 253.962,
      "size": 26,
      "deaths": 0,
      "tanks": 2,
      "healers": 6,
      "melee": 6,
      "ranged": 12,
      "server": {
        "id": 569,
        "name": "伊森利恩",
        "region": "CN"
      },
      "guild": {
        "id": 653912,
        "name": "四方",
        "faction": 1
      },
      "damageTaken": 88797903
    },
    {
      "rank": 24,
      "duration": 247280,
      "startTime": 1774267776522,
      "reportCode": "p2Hzkgd49GZ8PtKT",
      "fightId": 3,
      "reportStartTime": 1774267082372,
      "bracketData": 254.083,
      "size": 24,
      "deaths": 0,
      "tanks": 2,
      "healers": 5,
      "melee": 3,
      "ranged": 14,
      "server": {
        "id": 569,
        "name": "伊森利恩",
        "region": "CN"
      },
      "guild": {
        "id": 814941,
        "name": "妹妹说紫色很有韵味",
        "faction": 1
      },
      "damageTaken": 100643066
    },
    {
      "rank": 25,
      "duration": 247749,
      "startTime": 1774184529433,
      "reportCode": "MQf64nXCYAwRBb8V",
      "fightId": 16,
      "reportStartTime": 1774180783632,
      "bracketData": 250.957,
      "size": 23,
      "deaths": 0,
      "tanks": 2,
      "healers": 4,
      "melee": 3,
      "ranged": 14,
      "server": {
        "id": 566,
        "name": "亡语者",
        "region": "CN"
      },
      "guild": {
        "id": 759062,
        "name": "星穹列车",
        "faction": 1
      },
      "damageTaken": 89179566
    },
    {
      "rank": 26,
      "duration": 247926,
      "startTime": 1774267365679,
      "reportCode": "QvHmD6fxyXw9h3GM",
      "fightId": 9,
      "reportStartTime": 1774265401097,
      "bracketData": 252.56,
      "size": 25,
      "deaths": 1,
      "tanks": 2,
      "healers": 5,
      "melee": 6,
      "ranged": 12,
      "server": {
        "id": 666,
        "name": "布兰卡德",
        "region": "CN"
      },
      "guild": {
        "id": 783712,
        "name": "炉火糖粥2团",
        "faction": 1
      },
      "damageTaken": 107569571
    },
    {
      "rank": 27,
      "duration": 248314,
      "startTime": 1774010781655,
      "reportCode": "BpCRzjJGngXLdmFT",
      "fightId": 9,
      "reportStartTime": 1774007346544,
      "bracketData": 251.538,
      "size": 26,
      "deaths": 2,
      "tanks": 2,
      "healers": 5,
      "melee": 9,
      "ranged": 10,
      "server": {
        "id": 842,
        "name": "迅捷微风",
        "region": "CN"
      },
      "guild": {
        "id": 80764,
        "name": "暮雨南歌",
        "faction": 1
      },
      "damageTaken": 95243194
    },
    {
      "rank": 28,
      "duration": 248561,
      "startTime": 1774274080928,
      "reportCode": "cgAyZ21Dv7JKCTRG",
      "fightId": 41,
      "reportStartTime": 1774267758414,
      "bracketData": 252.133,
      "size": 30,
      "deaths": 0,
      "tanks": 2,
      "healers": 6,
      "melee": 10,
      "ranged": 12,
      "server": {
        "id": 720,
        "name": "死亡之翼",
        "region": "CN"
      },
      "guild": {
        "id": 581610,
        "name": "N.Aurora",
        "faction": 1
      },
      "damageTaken": 120476998
    },
    {
      "rank": 29,
      "duration": 249355,
      "startTime": 1774008846388,
      "reportCode": "yTVAmW7QcXqbt2nf",
      "fightId": 5,
      "reportStartTime": 1774008163441,
      "bracketData": 249.724,
      "size": 29,
      "deaths": 3,
      "tanks": 2,
      "healers": 6,
      "melee": 9,
      "ranged": 12,
      "server": {
        "id": 770,
        "name": "白银之手",
        "region": "CN"
      },
      "guild": {
        "id": 770959,
        "name": "红莲净土",
        "faction": 0
      },
      "damageTaken": 141894488
    },
    {
      "rank": 30,
      "duration": 249826,
      "startTime": 1774181424147,
      "reportCode": "f8TRQcG42krhvxyN",
      "fightId": 44,
      "reportStartTime": 1774166819144,
      "bracketData": 252.071,
      "size": 28,
      "deaths": 0,
      "tanks": 2,
      "healers": 5,
      "melee": 9,
      "ranged": 12,
      "server": {
        "id": 816,
        "name": "萨尔",
        "region": "CN"
      },
      "guild": {
        "id": 543731,
        "name": "疯人谷",
        "faction": 1
      },
      "damageTaken": 110484754
    },
    {
      "rank": 31,
      "duration": 249841,
      "startTime": 1774269504727,
      "reportCode": "9Vr7ktJha6nPbZA4",
      "fightId": 2,
      "reportStartTime": 1774267178942,
      "bracketData": 253.033,
      "size": 30,
      "deaths": 0,
      "tanks": 2,
      "healers": 5,
      "melee": 9,
      "ranged": 14,
      "server": {
        "id": 750,
        "name": "燃烧之刃",
        "region": "CN"
      },
      "guild": {
        "id": 802247,
        "name": "直到尽头-触帝",
        "faction": 1
      },
      "damageTaken": 132659094
    },
    {
      "rank": 32,
      "duration": 250097,
      "startTime": 1774016052625,
      "reportCode": "NVLk9haTKgXnF2Qb",
      "fightId": 32,
      "reportStartTime": 1774007349557,
      "bracketData": 248.929,
      "size": 28,
      "deaths": 0,
      "tanks": 2,
      "healers": 5,
      "melee": 9,
      "ranged": 12,
      "server": {
        "id": 778,
        "name": "神圣之歌",
        "region": "CN"
      },
      "guild": {
        "id": 265989,
        "name": "逐风",
        "faction": 0
      },
      "damageTaken": 127744983
    },
    {
      "rank": 33,
      "duration": 250122,
      "startTime": 1774099023945,
      "reportCode": "NTZgfYMF6xdtKDGv",
      "fightId": 76,
      "reportStartTime": 1774088292629,
      "bracketData": 252.667,
      "size": 30,
      "deaths": 1,
      "tanks": 2,
      "healers": 6,
      "melee": 6,
      "ranged": 16,
      "server": {
        "id": 575,
        "name": "克尔苏加德",
        "region": "CN"
      },
      "guild": {
        "id": 757763,
        "name": "桃喜奶屋",
        "faction": 1
      },
      "damageTaken": 136338574
    },
    {
      "rank": 34,
      "duration": 250218,
      "startTime": 1773884529542,
      "reportCode": "DFYPGj7hzZQM3k4A",
      "fightId": 9,
      "reportStartTime": 1773882914067,
      "bracketData": 243.5,
      "size": 30,
      "deaths": 0,
      "tanks": 2,
      "healers": 5,
      "melee": 10,
      "ranged": 13,
      "server": {
        "id": 666,
        "name": "布兰卡德",
        "region": "CN"
      },
      "guild": {
        "id": 704695,
        "name": "清水",
        "faction": 1
      },
      "damageTaken": 124500485
    },
    {
      "rank": 35,
      "duration": 250802,
      "startTime": 1774017980943,
      "reportCode": "8xT6LbPCApqrhGjy",
      "fightId": 6,
      "reportStartTime": 1774017076605,
      "bracketData": 250,
      "size": 25,
      "deaths": 0,
      "tanks": 2,
      "healers": 5,
      "melee": 7,
      "ranged": 11,
      "server": {
        "id": 826,
        "name": "血色十字军",
        "region": "CN"
      },
      "guild": {
        "id": 610813,
        "name": "所了哇多卡那",
        "faction": 1
      },
      "damageTaken": 109704045
    },
    {
      "rank": 36,
      "duration": 251811,
      "startTime": 1774273478181,
      "reportCode": "g8TqJfYVAjaZxBwz",
      "fightId": 14,
      "reportStartTime": 1774246458082,
      "bracketData": 252.828,
      "size": 29,
      "deaths": 0,
      "tanks": 2,
      "healers": 6,
      "melee": 8,
      "ranged": 13,
      "server": {
        "id": 874,
        "name": "雷克萨",
        "region": "CN"
      },
      "guild": {
        "id": 573179,
        "name": "THE SHADOWS",
        "faction": 0
      },
      "damageTaken": 110849499
    },
    {
      "rank": 37,
      "duration": 252358,
      "startTime": 1774272575675,
      "reportCode": "2BymczCJa7nTVkwA",
      "fightId": 6,
      "reportStartTime": 1774271051131,
      "bracketData": 252.423,
      "size": 26,
      "deaths": 1,
      "tanks": 2,
      "healers": 6,
      "melee": 6,
      "ranged": 12,
      "server": {
        "id": 826,
        "name": "血色十字军",
        "region": "CN"
      },
      "guild": {
        "id": 747451,
        "name": "Diamonds-cn",
        "faction": 1
      },
      "damageTaken": 110934792
    },
    {
      "rank": 38,
      "duration": 252853,
      "startTime": 1774271259289,
      "reportCode": "9CXDxT73qdmpQwFh",
      "fightId": 8,
      "reportStartTime": 1774268788599,
      "bracketData": 251.833,
      "size": 30,
      "deaths": 1,
      "tanks": 2,
      "healers": 5,
      "melee": 8,
      "ranged": 15,
      "server": {
        "id": 874,
        "name": "雷克萨",
        "region": "CN"
      },
      "guild": {
        "id": 751710,
        "name": "这次我请",
        "faction": 0
      },
      "damageTaken": 137191200
    },
    {
      "rank": 39,
      "duration": 252932,
      "startTime": 1774196464829,
      "reportCode": "gZYJpB13xQ2bThWG",
      "fightId": 3,
      "reportStartTime": 1774191258167,
      "bracketData": 251.357,
      "size": 28,
      "deaths": 1,
      "tanks": 2,
      "healers": 5,
      "melee": 6,
      "ranged": 15,
      "server": {
        "id": 591,
        "name": "加基森",
        "region": "CN"
      },
      "guild": {
        "id": 770214,
        "name": "午夜旋律",
        "faction": 1
      },
      "damageTaken": 121712615
    },
    {
      "rank": 40,
      "duration": 253079,
      "startTime": 1774181537556,
      "reportCode": "1Dh4j9yRqWBQmPYX",
      "fightId": 2,
      "reportStartTime": 1774179187883,
      "bracketData": 252.433,
      "size": 30,
      "deaths": 0,
      "tanks": 2,
      "healers": 6,
      "melee": 9,
      "ranged": 13,
      "server": {
        "id": 832,
        "name": "贫瘠之地",
        "region": "CN"
      },
      "guild": {
        "id": 525484,
        "name": "老友俱乐部",
        "faction": 0
      },
      "damageTaken": 135413148
    },
    {
      "rank": 41,
      "duration": 253361,
      "startTime": 1774268265183,
      "reportCode": "HyP2hKbptnzRJ673",
      "fightId": 8,
      "reportStartTime": 1774266010290,
      "bracketData": 252.741,
      "size": 27,
      "deaths": 1,
      "tanks": 2,
      "healers": 5,
      "melee": 10,
      "ranged": 10,
      "server": {
        "id": 676,
        "name": "影之哀伤",
        "region": "CN"
      },
      "guild": {
        "id": 452961,
        "name": "无名之辈",
        "faction": 1
      },
      "damageTaken": 119213022
    },
    {
      "rank": 42,
      "duration": 253504,
      "startTime": 1774186183985,
      "reportCode": "j3fLCZHvahRpVdzc",
      "fightId": 11,
      "reportStartTime": 1774180448681,
      "bracketData": 251.655,
      "size": 29,
      "deaths": 1,
      "tanks": 2,
      "healers": 6,
      "melee": 10,
      "ranged": 11,
      "server": {
        "id": 835,
        "name": "达克萨隆",
        "region": "CN"
      },
      "guild": {
        "id": 269298,
        "name": "水墨江南",
        "faction": 1
      },
      "damageTaken": 119506305
    },
    {
      "rank": 43,
      "duration": 253916,
      "startTime": 1774259045425,
      "reportCode": "mAgq6pwbJCPFfkQB",
      "fightId": 9,
      "reportStartTime": 1774257834918,
      "bracketData": 245.767,
      "size": 30,
      "deaths": 0,
      "tanks": 2,
      "healers": 6,
      "melee": 7,
      "ranged": 15,
      "server": {
        "id": 697,
        "name": "无尽之海",
        "region": "CN"
      },
      "guild": {
        "id": 787590,
        "name": "B L C",
        "faction": 1
      },
      "damageTaken": 127430990
    },
    {
      "rank": 44,
      "duration": 254139,
      "startTime": 1774099544553,
      "reportCode": "DLBR4gA7mX8PjKqV",
      "fightId": 33,
      "reportStartTime": 1774092755023,
      "bracketData": 248.867,
      "size": 30,
      "deaths": 0,
      "tanks": 2,
      "healers": 6,
      "melee": 10,
      "ranged": 12,
      "server": {
        "id": 676,
        "name": "影之哀伤",
        "region": "CN"
      },
      "guild": {
        "id": 11917,
        "name": "傲  血  荣  耀",
        "faction": 1
      },
      "damageTaken": 118319525
    },
    {
      "rank": 45,
      "duration": 254208,
      "startTime": 1774180851357,
      "reportCode": "AnVP2vfmF7Tkb4BC",
      "fightId": 36,
      "reportStartTime": 1774157049975,
      "bracketData": 251.233,
      "size": 30,
      "deaths": 0,
      "tanks": 2,
      "healers": 5,
      "melee": 7,
      "ranged": 16,
      "server": {
        "id": 826,
        "name": "血色十字军",
        "region": "CN"
      },
      "guild": {
        "id": 765440,
        "name": "呼风唤鱼",
        "faction": 1
      },
      "damageTaken": 121125198
    },
    {
      "rank": 46,
      "duration": 255162,
      "startTime": 1774269749987,
      "reportCode": "6kxh49n3d1TjCgFL",
      "fightId": 11,
      "reportStartTime": 1774247624169,
      "bracketData": 252.448,
      "size": 29,
      "deaths": 0,
      "tanks": 2,
      "healers": 6,
      "melee": 10,
      "ranged": 11,
      "server": {
        "id": 770,
        "name": "白银之手",
        "region": "CN"
      },
      "guild": {
        "id": 532293,
        "name": "Doraemon",
        "faction": 0
      },
      "damageTaken": 125747650
    },
    {
      "rank": 47,
      "duration": 255401,
      "startTime": 1774015084612,
      "reportCode": "8wVX7TMNBLn4fphj",
      "fightId": 41,
      "reportStartTime": 1774006573101,
      "bracketData": 249.966,
      "size": 29,
      "deaths": 3,
      "tanks": 2,
      "healers": 5,
      "melee": 8,
      "ranged": 14,
      "server": {
        "id": 676,
        "name": "影之哀伤",
        "region": "CN"
      },
      "guild": {
        "id": 569063,
        "name": "岁岁平安",
        "faction": 1
      },
      "damageTaken": 120832865
    },
    {
      "rank": 48,
      "duration": 255710,
      "startTime": 1774010686895,
      "reportCode": "ABjfNty7wJprXF3z",
      "fightId": 4,
      "reportStartTime": 1774008374593,
      "bracketData": 249.444,
      "size": 27,
      "deaths": 0,
      "tanks": 2,
      "healers": 5,
      "melee": 9,
      "ranged": 11,
      "server": {
        "id": 790,
        "name": "罗宁",
        "region": "CN"
      },
      "guild": {
        "id": 298585,
        "name": "繁梦",
        "faction": 0
      },
      "damageTaken": 121958618
    },
    {
      "rank": 49,
      "duration": 256178,
      "startTime": 1774269707593,
      "reportCode": "wRdVhgktF9KqXaYy",
      "fightId": 13,
      "reportStartTime": 1774266337450,
      "bracketData": 252.667,
      "size": 30,
      "deaths": 1,
      "tanks": 2,
      "healers": 6,
      "melee": 7,
      "ranged": 15,
      "server": {
        "id": 720,
        "name": "死亡之翼",
        "region": "CN"
      },
      "guild": {
        "id": 770988,
        "name": "灬红莲火灬",
        "faction": 1
      },
      "damageTaken": 152190095
    },
    {
      "rank": 50,
      "duration": 256368,
      "startTime": 1774273983026,
      "reportCode": "XQGVWMDKahjkvpT6",
      "fightId": 3,
      "reportStartTime": 1774272729486,
      "bracketData": 252.12,
      "size": 25,
      "deaths": 0,
      "tanks": 2,
      "healers": 5,
      "melee": 5,
      "ranged": 13,
      "server": {
        "id": 720,
        "name": "死亡之翼",
        "region": "CN"
      },
      "guild": {
        "id": 595968,
        "name": "指间电竞",
        "faction": 1
      },
      "damageTaken": 109099431
    }
  ]
}
